{"forum": {"content": "<br />\u6211\u6709\u9593\u623f<br />\u623f\u79df\u662f\u4fe1\u4efb<br />\u4f60\u9858\u610f\u7576\u90a3\u500b\u623f\u5ba2\u55ce", "images": ["http://filestoresg1.beetalkmobile.com:8081/file/c9f7088a6deaf5bfb1b349431d2a94df"], "urls": [], "title": "\u60f3\u8a8d\u8b58\u5e95\u8fea\ud83d\ude0a\ud83d\ude0a"}, "threadStatus": 1, "regionId": 886, "barStatus": 0, "barId": 734, "postBy": {"utc": 1513682963000, "level": 5, "location": "", "avatar": "http://filestoresg1.beetalkmobile.com:8081/file/2", "name": "User blocked"}, "id": 7277601}
