{"forum": {"content": "\u6700\u8fd1\u6709\u5e7e\u90e8\u4e0d\u932f\u7684\u96fb\u5f71\u4e0a\u6620\u4e86!!<br />\u5e36\u6211\u53bb\u6708\u7403\uff0c\u5947\u8e5f\u7537\u5b69balabala<br />\u5f88\u60f3\u627e\u670b\u53cb\u4e00\u8d77\u53bb\u770b<br />\u53ef\u60dc\u670b\u53cb\u4e0d\u662f\u6c92\u8208\u8da3\u5c31\u662f\u6c92\u7a7a<br />\u537b\u53c8\u4e0d\u60f3\u932f\u904e\u597d\u96fb\u5f71\ud83d\ude29<br />\u5982\u679c\u4f60\u5c0d\u9019\u5169\u90e8\u96fb\u5f71\u6709\u8208\u8da3<br />\u9084\u662f\u6709\u5176\u4ed6\u63a8\u85a6\u7684\u96fb\u5f71\u60f3\u63ea\u4eba\u4e00\u8d77\u53bb\u770b<br />\u90fd\u53ef\u4ee5\u627e\u6211\u512a~\ud83d\ude06\ud83d\ude06<br />", "images": [], "urls": [{"url": "https://youtu.be/xdXUgfY-1L8", "thumbUrl": "https://i.ytimg.com/vi/xdXUgfY-1L8/maxresdefault.jpg", "description": "\u661f\u6cf0\u5a1b\u6a02 https://www.facebook.com/SHINETIME2017/ \u96fb\u5f71\u3010\u5e36\u6211\u53bb\u6708\u7403\u3011\uff1ahttps://www.facebook.com/takemetothemoon2017 ", "title": "\u96fb\u5f71\u3010\u5e36\u6211\u53bb\u6708\u7403\u3011\u5b98\u65b9\u6b63\u5f0f\u9810\u544aOfficial Trailer HD-12\u67081\u65e5\u628a\u6211\u6700\u597d\u7684\u611b\u7559\u7d66\u4f60\uff01"}], "title": "\u5fb5\u53f0\u5357\u4e00\u8d77\u770b\u96fb\u5f71\u7684\u670b\u53cb\ud83d\ude00"}, "threadStatus": 0, "regionId": 886, "barStatus": 0, "barId": 47, "postBy": {"utc": 1512996488000, "level": 2, "location": "\u53f0\u5357\u5e02\u00b7\u53f0\u7063", "avatar": "http://filestoresg1.beetalkmobile.com:8081/file/-4885558948497427731", "name": "\u5a03\u5a03"}, "id": 7222068}
