{"forum": {"content": "\u72fc\u6709\u60c5   \u59b9\u7121\u610f<br />\u8b8a\u614b\u5f80\u5f8c\u65e5\u5b50\u6709\u4f60\u53d7\u4e86<br />\u61f8\u5d16\u52d2\u99ac  \u6709\u72af\u7f6a\u52d5\u6a5f\u7684\u4eba\u5011", "images": ["http://filestoresg1.beetalkmobile.com:8081/file/df837e5843597c6480a31f87f4a61995"], "urls": [], "title": "\u75c5\u4e86"}, "threadStatus": 1, "regionId": 886, "barStatus": 0, "barId": 13, "postBy": {"utc": 1512997813000, "level": 7, "location": "\u65b0\u5317\u5e02\u00b7\u53f0\u7063", "avatar": "http://filestoresg1.beetalkmobile.com:8081/file/311876495058697175", "name": "\u9b54\u6b63\u718a"}, "id": 7222216}
