{"forum": {"content": "\u4eca\u5e74\u6536\u5230\u7684\u79ae\u76d2\uff0c\u6eff\u6709\u5275\u610f\u7684<br /><br />\u88e1\u9762\u7684\u714e\u9905\u4e5f\u6eff\u597d\u5403\u7684\uff0c\u4e0d\u6703\u592a\u751c~~<br />", "images": ["http://filestoresg1.beetalkmobile.com:8081/file/6ab730fa99e46e69892dcaeb4b599a56", "http://filestoresg1.beetalkmobile.com:8081/file/0356a0e906257acece730e18ee38e27a"], "urls": [], "title": "\u904e\u5e74\u79ae\u76d2 \u5609\u51a0\u559c\u714e\u9905"}, "threadStatus": 0, "regionId": 886, "barStatus": 0, "barId": 98, "postBy": {"utc": 1518658157000, "level": 8, "location": "\u53f0\u4e2d\u5e02\u00b7\u53f0\u7063", "avatar": "http://filestoresg1.beetalkmobile.com:8081/file/3289130761835397347", "name": "\u8ca2\u8ca2\u9999\ud83c\udf54"}, "id": 7713827}
