{"forum": {"content": "\u4f60\u5011\u600e\u6a23\u7559\u4f4f\u5e25\u54e5\u7684\u5462\uff1f\u544a\u8a34\u6211\u4f60\u5011\u7684\u9b45\u529b\uff0c\u6216\u662f\u4f60\u5011\u7684\u5efa\u8b70\u54c8\u54c8\u54c8", "images": ["http://filestoresg1.beetalkmobile.com:8081/file/f39cd5672166e80c067db7d35339e192"], "urls": [], "title": "\u5e25\u54e5\u5f88\u96e3\u7559\u4f4f\u55da\u55da\ud83d\ude2d\ud83d\ude2d\ud83d\ude2d"}, "threadStatus": 0, "regionId": 886, "barStatus": 0, "barId": 4, "postBy": {"utc": 1515304113000, "level": 1, "location": "\u82b1\u84ee\u7e23\u00b7\u53f0\u7063", "avatar": "http://filestoresg1.beetalkmobile.com:8081/file/-708244916330140160", "name": "\u83ca\u82b1\u6eff\u5929\u98db\u963f\u98db"}, "id": 7411195}
