{"forum": {"content": "\u627e\u6211\u804a\u804a\u5427", "images": ["http://filestoresg1.beetalkmobile.com:8081/file/c454539f33db7a729d70f265bea61c67", "http://filestoresg1.beetalkmobile.com:8081/file/08d463a0ea751287c4fcce01314d1269"], "urls": [], "title": "\u55ae\u8eab"}, "threadStatus": 0, "regionId": 886, "barStatus": 0, "barId": 205, "postBy": {"utc": 1518796061000, "level": 0, "location": "\u53f0\u4e2d\u5e02\u00b7\u53f0\u7063", "avatar": "http://filestoresg1.beetalkmobile.com:8081/file/-6866843716278436990", "name": "Cheng Garfield"}, "id": 7725829}
