{"forum": {"content": "\u5149\u5fa9\u65b0\u6751", "images": ["http://filestoresg1.beetalkmobile.com:8081/file/b8d9410a033fd7912b285beb6ffdf46d", "http://filestoresg1.beetalkmobile.com:8081/file/a2bea630feb5dd8f42349e9ef47bbe46", "http://filestoresg1.beetalkmobile.com:8081/file/6ee29e804ed8df587ce7e6f151431c09", "http://filestoresg1.beetalkmobile.com:8081/file/c9c139708826307632251ac3a4d5e2f2", "http://filestoresg1.beetalkmobile.com:8081/file/a7441a21c94567338ae97378c245568d"], "urls": [], "title": "\u5149\u5fa9\u65b0\u6751"}, "threadStatus": 0, "regionId": 886, "barStatus": 0, "barId": 85, "postBy": {"utc": 1513754211000, "level": 4, "location": "", "avatar": "http://filestoresg1.beetalkmobile.com:8081/file/5142778723121170176", "name": "Care"}, "id": 7283144}
