{"forum": {"content": "\u7121\u804a\u53ef\u4ee5\u52a0\u6211<br />\u53cd\u6b63\u59b3\u4e5f\u7121\u804a", "images": ["http://filestoresg1.beetalkmobile.com:8081/file/93b8d3864807b0941e7aaf42e95bba39"], "urls": [], "title": "\u65e9\u5b89"}, "threadStatus": 0, "regionId": 886, "barStatus": 0, "barId": 205, "postBy": {"utc": 1512168790000, "level": 2, "location": "\u65b0\u5317\u5e02\u00b7\u53f0\u7063", "avatar": "http://filestoresg1.beetalkmobile.com:8081/file/-132779222154789115", "name": "\u6211\u53eb\u963f\u9f4a\u963f\u9f4a\u7684\u963f\u963f\u9f4a\u7684\u9f4a"}, "id": 7153291}
