{"forum": {"content": "\u4e00\u8d77\u804a\u5929\u8d1d\ud83d\ude01\ud83d\ude01", "images": ["http://filestoresg1.beetalkmobile.com:8081/file/b0a990a0743ef766226ccd3247638413"], "urls": [], "title": "\u4ea4\u670b\u53cb"}, "threadStatus": 0, "regionId": 886, "barStatus": 0, "barId": 786, "postBy": {"utc": 1513406980000, "level": 1, "location": "\u65b0\u5317\u5e02\u00b7\u53f0\u7063", "avatar": "http://filestoresg1.beetalkmobile.com:8081/file/4806561271324064193", "name": "\u5c0f\u7fbd"}, "id": 7255189}
