{"forum": {"content": "\u4e94\u6bba", "images": ["http://filestoresg1.beetalkmobile.com:8081/file/2516af2c44ec73e90907fd9513ca18a4"], "urls": [], "title": "\u6700\u8fd1\u60f3\u5982\u4f55\u7528\u5766 "}, "threadStatus": 0, "regionId": 886, "barStatus": 0, "barId": 841, "postBy": {"utc": 1510996267000, "level": 2, "location": "\u9ad8\u96c4\u5e02\u00b7\u53f0\u7063", "avatar": "http://filestoresg1.beetalkmobile.com:8081/file/-2443458968662083360", "name": "\u5927\u5bf6(\u6bf3\u660d)"}, "id": 7058943}
