{"forum": {"content": "\u6c92\u4eba\u7d04~ \u53ea\u80fd\u5728\u5bb6\u770b\u76f4\u64ad  \u6574\u500b\u4eba\u597d\u5ee2  \u60f3\u627e\u500b\u4eba\u966a\u4e00\u4e0b \u804a\u804a\u5929", "images": [], "urls": [{"url": "https://www.facebook.com/V7%E5%BE%A9%E5%88%BB%E7%B2%BE%E5%93%81-1788360564517550/", "thumbUrl": "https://lookaside.fbsbx.com/lookaside/crawler/media/?media_id=1788360564517550", "description": "V7\u5fa9\u523b\u7cbe\u54c1. 107 likes \u00b7 3 talking about this. Brand", "title": "V7\u5fa9\u523b\u7cbe\u54c1"}], "title": "\u8056\u8a95\u7bc0\u6c92\u4eba\u7d04~"}, "threadStatus": 0, "regionId": 886, "barStatus": 0, "barId": 7, "postBy": {"utc": 1514203941000, "level": 1, "location": "", "avatar": "http://filestoresg1.beetalkmobile.com:8081/file/4693412741498058346", "name": "\u4f73\u742a"}, "id": 7318938}
