{"forum": {"content": "\u5687\u4e00\u8df3 @@    \u8981\u7b4910\u79d2\u54e6\uff01", "images": ["http://filestoresg1.beetalkmobile.com:8081/file/9512d6a6f08b44da0543b95a20aa7db1"], "urls": [], "title": "\u7f8e\u5973 ^^\u2026\u2026"}, "threadStatus": 0, "regionId": 886, "barStatus": 0, "barId": 10, "postBy": {"utc": 1514421258000, "level": 25, "location": "\u53f0\u7063", "avatar": "http://filestoresg1.beetalkmobile.com:8081/file/-5739484760241883541", "name": "\u4e00\u8449\u5b50\u4e00 \ud83c\udf43"}, "id": 7336883}
