{"forum": {"content": "\u5f04\u9019\u4e00\u982d\u50cf\u6d0b\u5a03\u5a03\u5377\u5ea6\uff0c\u8981\u55c6\u4eba\u5f88\u6c92\u529b\uff01<br />\u4e0d\u904e\u5c31\u662f\u5e74\u904e40\u5f8c\u2026\u2026\u2026\uff08\uff09\u5e74\u7d00", "images": ["http://filestoresg1.beetalkmobile.com:8081/file/33676dc216c3583047bf5dbbaf21807d"], "urls": [], "title": "\u6c38\u906045"}, "threadStatus": 0, "regionId": 886, "barStatus": 0, "barId": 782, "postBy": {"utc": 1521116368000, "level": 1, "location": "\u53f0\u5317\u5e02\u00b7\u53f0\u7063", "avatar": "http://filestoresg1.beetalkmobile.com:8081/file/-1250067749977186426", "name": "ling\u676f\u676f\uff0840\u4ee5\u4e0a\u5927\u5b38\uff09"}, "id": 7946921}
