{"forum": {"content": "\u9019\u9ebc\u5927\u7684\u9bfd\u9b5a \u5c3a\u9bfd", "images": ["http://filestoresg1.beetalkmobile.com:8081/file/e5162c86084062283c09bf8258fcb90c", "http://filestoresg1.beetalkmobile.com:8081/file/95da7436d61a19f3020a1615c3f78d75"], "urls": [], "title": "\u91ce\u751f\u9bfd\u9b5a"}, "threadStatus": 0, "regionId": 886, "barStatus": 0, "barId": 723, "postBy": {"utc": 1519128024000, "level": 21, "location": "\u65b0\u5317\u5e02\u00b7\u53f0\u7063", "avatar": "http://filestoresg1.beetalkmobile.com:8081/file/-6042706994810927208", "name": "\u9673\u7384\u5958"}, "id": 7755278}
