{"forum": {"content": "\u7bb1\u76d2\u98ef(\u4e2d)+\u975c\u5ca1\u7da0\u8336\u53ef\u6a02", "images": ["http://filestoresg1.beetalkmobile.com:8081/file/775b07020b87e2e0b6a2ef299f038b06", "http://filestoresg1.beetalkmobile.com:8081/file/265dfe807772830729110ba7b59ea043", "http://filestoresg1.beetalkmobile.com:8081/file/5237c0c9d44f68dcb1f07b2a882a56c4", "http://filestoresg1.beetalkmobile.com:8081/file/fdfdc9428e1fe5579c2d680059ac8716", "http://filestoresg1.beetalkmobile.com:8081/file/d6882b46a201201106b90daa972d3bfa", "http://filestoresg1.beetalkmobile.com:8081/file/a139cb9fb17b672afff33d6c1125a465"], "urls": [], "title": "\u65e5\u672c\u6a4b \u7389\u4e3c\u9c3b\u9b5a\u98ef"}, "threadStatus": 0, "regionId": 886, "barStatus": 0, "barId": 98, "postBy": {"utc": 1512555748000, "level": 17, "location": "\u53f0\u5317\u5e02\u00b7\u53f0\u7063", "avatar": "http://filestoresg1.beetalkmobile.com:8081/file/8409351918908481821", "name": "\u8521\u963f\u68ee"}, "id": 7184919}
