{"forum": {"content": "\u4f86\u804a\u5929\u554a", "images": ["http://filestoresg1.beetalkmobile.com:8081/file/ae1cd8da6be2e815dc833683dc3aecb9"], "urls": [], "title": "\u597d\u7121\u804a"}, "threadStatus": 0, "regionId": 886, "barStatus": 0, "barId": 20, "postBy": {"utc": 1516412571000, "level": 4, "location": "\u65b0\u7af9\u7e23\u00b7\u53f0\u7063", "avatar": "http://filestoresg1.beetalkmobile.com:8081/file/4889173068898810631", "name": "\u897f\u74dc\u5471\u5471\u53eb\ud83c\udf49\ud83c\udf49"}, "id": 7510905}
