{"forum": {"content": "\u62113/10\u771f\u7684\u662f\u6709\u611f\u89ba\u5230\u662f\u8001\u8f1d\u4ed4==\u4f60\uff0c\u59b3\u5462\uff1f", "images": ["http://filestoresg1.beetalkmobile.com:8081/file/854a208f8a6836dcb6b38b8240a39a19"], "urls": [], "title": "\u5931\u7720\u591c\u7121\u804a\u901b\u901b74\u7684\u6253\u53f3\u4e00\u4e0b\ud83d\ude04"}, "threadStatus": 0, "regionId": 886, "barStatus": 0, "barId": 747, "postBy": {"utc": 1514580659000, "level": 12, "location": "\u53f0\u4e2d\u5e02\u00b7\u53f0\u7063", "avatar": "http://filestoresg1.beetalkmobile.com:8081/file/-3300075278484159831", "name": "\u5289\u5c09\u7965"}, "id": 7350336}
