{"forum": {"content": "\u5229\u7528\u4e0b\u73ed\u6642\u9593\u4e00\u9ede\u4e00\u9ede\u7684\u6162\u6162\u6574\u7406<br />\u6574\u7406\u5230\u73fe\u5728\u9019\u6a23\u8d85\u6709\u6210\u5c31\u611f\u7684<br />\uff08\u4e00\u500b\u79ae\u62dc\u5c31\u9019\u6a23\u904e\u53bb\u4e86....\uff09<br /><br />\u73fe\u5728\u53ea\u5269\u4e0b\u660e\u5929\u7b49\u7a97\u7c3e\u9001\u6d17\u56de\u4f86<br />\u5c31\u8fd1\u4e4e\u5b8c\u7f8e\u5566<br />\ud83d\ude0e\ud83d\ude0e\ud83d\ude0e<br /><br />\u4ee5\u4e0b\u9644\u4e0a\u5c0d\u7167\u5716<br />\u53e6\u5fb5\u4e00\u4f4d\u5973\u670b\u53cb<br />\u6709\u6c92\u6709\u4eba\u9858\u610f\u966a\u6211\u4e00\u8d77\u671f\u5f85\u64c1\u6709\u5f7c\u6b64\u7684\u6bcf\u4e00\u500b\u660e\u5929\uff1f\uff01<br />\ud83e\udd14\ud83e\udd14\ud83e\udd14", "images": ["http://filestoresg1.beetalkmobile.com:8081/file/d202a5477bf1012ecbc024cb82bd7bab", "http://filestoresg1.beetalkmobile.com:8081/file/456a47475ae9746dc0c80c9fd39a3aa1", "http://filestoresg1.beetalkmobile.com:8081/file/06e9226d056f896792f0bc63ffc8efb5", "http://filestoresg1.beetalkmobile.com:8081/file/6dcc80af61c636d7d69f581d2dcb0720", "http://filestoresg1.beetalkmobile.com:8081/file/7bf0636abc1b31d9cdc2a8fa51fd91a4", "http://filestoresg1.beetalkmobile.com:8081/file/42dffc536aebe4edb5ab10610c23bc5b"], "urls": [], "title": "\uff08\u9727\u5cf029\u55ae4\u5e74\uff09\u4eca\u5929\u7d42\u65bc\u6574\u7406\u597d\u5957\u623f\u4e86\uff0c\u958b\u5fc3"}, "threadStatus": 0, "regionId": 886, "barStatus": 0, "barId": 205, "postBy": {"utc": 1521020338000, "level": 1, "location": "\u53f0\u4e2d\u5e02\u00b7\u53f0\u7063", "avatar": "http://filestoresg1.beetalkmobile.com:8081/file/-7453302333579986870", "name": "\u6b64\u5e33\u6236\u505c\u7528\uff0c\u4e0d\u958b\u4e86\uff01\uff01"}, "id": 7937230}
