{"forum": {"content": "\u5225\u5728\u5f9e\u5916\u8868\u8a8d\u8b58\u6211<br />\u53ea\u6c42\u7a69\u5b9a\u5171\u4f34\u7684\u5c0d\u8c61<br />\u672c\u4eba\u9664\u4e86\u7159 \u7121\u4e0d\u826f\u55dc\u597d<br />\u6709\u9ede\u5de5\u4f5c\u72c2 \u6708\u6536\u843d\u572850\uff5e60k<br />\u80fd\u63a5\u53d7\u5c31\u4f86\u79c1\u6211<br />\u8ac7\u8ac7\u660e\u5e74\u7684\u672a\u4f86", "images": ["http://filestoresg1.beetalkmobile.com:8081/file/35d78bf08d7f648830c53a532eefb759", "http://filestoresg1.beetalkmobile.com:8081/file/6c0a2f220cdfb2fef66d90ec1009bd81"], "urls": [], "title": "\u627e\u500b\u7a69\u5b9a\u7684\u4f34"}, "threadStatus": 0, "regionId": 886, "barStatus": 0, "barId": 205, "postBy": {"utc": 1514546707000, "level": 1, "location": "\u65b0\u5317\u5e02\u00b7\u53f0\u7063", "avatar": "http://filestoresg1.beetalkmobile.com:8081/file/6399521619378860290", "name": "\u4f5b\u7cfb\u7537\u5b69"}, "id": 7347052}
