{"forum": {"content": "\u5fc3\u8840\u4f86\u6f6e\u60f3\u6234\u8033\u74b0<br />\u7d50\u679c\u7a7f\u4e0d\u904e<br />\u75db\u6b7b\u6211\u5566\uff01\ud83d\ude2d\ud83d\ude2d\ud83d\ude2d", "images": ["http://filestoresg1.beetalkmobile.com:8081/file/eb8542d988890ae6e39554f27ba8dc08"], "urls": [], "title": "\u592a\u4e45\u6c92\u6234\u8033\u74b0\u7684\u7d50\u679c"}, "threadStatus": 0, "regionId": 886, "barStatus": 0, "barId": 4, "postBy": {"utc": 1515812257000, "level": 3, "location": "\u65b0\u5317\u5e02\u00b7\u53f0\u7063", "avatar": "http://filestoresg1.beetalkmobile.com:8081/file/-7761370092965301556", "name": "Lin Shu Ting\ud83d\udc8b"}, "id": 7456351}
