{"forum": {"content": "\u661f", "images": ["http://filestoresg1.beetalkmobile.com:8081/file/b08d5a9ad98fedc2cad0f1f63ed862de", "http://filestoresg1.beetalkmobile.com:8081/file/cd3804e8f6d00cdb533b140a377c61f7", "http://filestoresg1.beetalkmobile.com:8081/file/9c7a8d3490aeb6107aaa94e461892076"], "urls": [], "title": "\u591c\u7a7a"}, "threadStatus": 0, "regionId": 886, "barStatus": 0, "barId": 77, "postBy": {"utc": 1516934703000, "level": 4, "location": "", "avatar": "http://filestoresg1.beetalkmobile.com:8081/file/4633591606546688526", "name": "Mr. Y"}, "id": 7559640}
