{"forum": {"content": "\u8ddf\u5e73\u5e38\u98a8\u683c\u5b8c\u5168\u4e0d\u4e00\u6a23\u7684\u89d2\u8272<br />\u7e3d\u89ba\u5f97\u5f88\u96e3\u99d5\u99ad\u02ca\u02c7\u02cb<br /><br />facebook\u7c89\u5c08-\u767d\u8c93\u3055\u307e\u5207\u958b\u662f\u9ed1\u7684https://www.facebook.com/srnksm1215/", "images": ["http://filestoresg1.beetalkmobile.com:8081/file/6e6bec6ead336d13ba72c53f459203d2"], "urls": [], "title": "\u4eca\u5e74\u7b2c\u4e00\u8a66w"}, "threadStatus": 0, "regionId": 886, "barStatus": 0, "barId": 34, "postBy": {"utc": 1516381646000, "level": 4, "location": "\u65b0\u5317\u5e02\u00b7\u53f0\u7063", "avatar": "http://filestoresg1.beetalkmobile.com:8081/file/3676380978054650877", "name": "\u767d\u8c93\u767d"}, "id": 7509072}
