{"forum": {"content": "\ud83c\udf78\ud83c\udf74\u7f8e\u5473", "images": ["http://filestoresg1.beetalkmobile.com:8081/file/b09d07d3380aa5ee86a75dd5a35f67cb", "http://filestoresg1.beetalkmobile.com:8081/file/2723bb580f1c61cc8583f533350e181f", "http://filestoresg1.beetalkmobile.com:8081/file/3dbbd4534aa40c17899c0a5643f16490", "http://filestoresg1.beetalkmobile.com:8081/file/d96f0d7786630639fa07a408c967eee0", "http://filestoresg1.beetalkmobile.com:8081/file/8ef5960a8f7d64ef023583fe4f8e76d2", "http://filestoresg1.beetalkmobile.com:8081/file/0d424971c7d80b8a765f1afc731c632a"], "urls": [], "title": "\u963f\u6839\u5ef7\u6162\u706b\u5ef6\u71d2\u725b\u6392"}, "threadStatus": 0, "regionId": 886, "barStatus": 0, "barId": 98, "postBy": {"utc": 1518257909000, "level": 21, "location": "", "avatar": "http://filestoresg1.beetalkmobile.com:8081/file/-6617790061123913196", "name": "Tang"}, "id": 7677697}
