{"forum": {"content": "\u6c42\u500b\u5c0f\u516c\u4e3b\u6c42\u500b\u7a69\ud83d\ude1e\ud83d\ude1e\ud83d\ude1e", "images": ["http://filestoresg1.beetalkmobile.com:8081/file/7fc0caf419037734ec5b48b3bb1553d7"], "urls": [], "title": "\u55ae\u8eab\ud83d\udc36"}, "threadStatus": 0, "regionId": 886, "barStatus": 0, "barId": 205, "postBy": {"utc": 1515994455000, "level": 2, "location": "\u53f0\u7063", "avatar": "http://filestoresg1.beetalkmobile.com:8081/file/820409398072773572", "name": "\u8def\u904e\u5225\u932f\u904e"}, "id": 7473098}
