{"forum": {"content": "\u95dc\u516c~<br />\u81ea\u5f9e\u8d64\u5154\u99ac\u5e74\u8001\u8dd1\u4e0d\u52d5\u5f8c\uff0c\u6211\u5c31\u63db\u4e86\u5750\u9a0e~~~~<br /><br />\u6316\u54a7\uff5e\u7adf\u7136\u8dd1\u5f97\u6bd4\u8d64\u5154\u99ac\u9084\u5feb~~(>\ufe4f<)", "images": ["http://filestoresg1.beetalkmobile.com:8081/file/7dd9f430a170c92beb267a8d245cbe55", "http://filestoresg1.beetalkmobile.com:8081/file/52714344131a063456724c2949719f33"], "urls": [], "title": "\u795e\u4e5f\u6297\u62d2\u4e0d\u4e86\u7684\u8a98\u60d1~^_^"}, "threadStatus": 0, "regionId": 886, "barStatus": 0, "barId": 10, "postBy": {"utc": 1510974280000, "level": 9, "location": "\u65b0\u5317\u5e02\u00b7\u53f0\u7063", "avatar": "http://filestoresg1.beetalkmobile.com:8081/file/7689817217445757722", "name": "Michael"}, "id": 7057007}
