{"forum": {"content": "\u90fd\u5df2\u7d93\u55ae\u8eab21\u5e74\u4e86 <br />\u60f3\u627e\u500b\u7a69\u4ea4\u4e5f\u597d\u96e3 <br />\u662f\u6211\u592a\u7b28\u9084\u662f\u6211\u4e0d\u6703\u8ffd\u5462\uff1f<br />#\u5716\u6587\u4e0d\u7b26", "images": ["http://filestoresg1.beetalkmobile.com:8081/file/d35a65e3f9e5ad526568c21befe1d61b"], "urls": [], "title": "\u55ae\u8eab21\u5e74"}, "threadStatus": 0, "regionId": 886, "barStatus": 0, "barId": 13, "postBy": {"utc": 1510671609000, "level": 3, "location": "", "avatar": "http://filestoresg1.beetalkmobile.com:8081/file/-5707806751415730428", "name": "\u963f\u97cb"}, "id": 7033173}
