{"forum": {"content": "\u6709\u4eba\u5728\u6d77\u6d0b\u5973\u795e\u55ce\uff1f", "images": ["http://filestoresg1.beetalkmobile.com:8081/file/f0ad07ccefd17a86536e4df5a35b09a3"], "urls": [], "title": "\u5929\u5802M \u6d77\u6d0b\u5973\u795e"}, "threadStatus": 0, "regionId": 886, "barStatus": 0, "barId": 59, "postBy": {"utc": 1514271451000, "level": 2, "location": "\u53f0\u5357\u5e02\u00b7\u53f0\u7063", "avatar": "http://filestoresg1.beetalkmobile.com:8081/file/4614218208201304326", "name": "\u963f\u52d7"}, "id": 7324328}
