{"forum": {"content": "\u591c\u9593\u96a8\u62cd", "images": ["http://filestoresg1.beetalkmobile.com:8081/file/98aa5d3d352249a5dbaed7dcc08307c4", "http://filestoresg1.beetalkmobile.com:8081/file/9edf90d4b8a38da2128c6fe5123a1d66", "http://filestoresg1.beetalkmobile.com:8081/file/45ab618dd7418c6b2b61e00c1c37bbaf", "http://filestoresg1.beetalkmobile.com:8081/file/67fc37728e375d78f80380559ec05aa6", "http://filestoresg1.beetalkmobile.com:8081/file/6e2e20a80a1dcd394bcc5a816adb1ae3", "http://filestoresg1.beetalkmobile.com:8081/file/a534cc2ee0e9634ed83bdf9d48b91e85"], "urls": [], "title": "\u7121\u9583\u71c8\u591c\u9593\u62cd\u651d"}, "threadStatus": 0, "regionId": 886, "barStatus": 0, "barId": 77, "postBy": {"utc": 1513893250000, "level": 6, "location": "\u53f0\u7063", "avatar": "http://filestoresg1.beetalkmobile.com:8081/file/3265461577505929645", "name": "\u9999\u7d72\u858f\u4ec1\u6ce5"}, "id": 7294149}
