{"forum": {"content": "~\u672c\u7626\u60f3\u8b8a\u58ef\u7a7f\u8863\u670d\u597d\u770b~", "images": ["http://filestoresg1.beetalkmobile.com:8081/file/08724ff8811cd220d60231a46ccb1e94"], "urls": [], "title": "\u8acb\u554f\u6211\u60f3\u589e\u808c\u58ef\uff0c\u76ee\u524d171-58\uff0c\u6709\u9ad8\u96c4\u7684\u670b\u53cb\u4e00\u8d77\u7df4\u561b~\u6211\u6c92\u57fa\u790e\u5f9e0\u958b\u59cb\uff01\u4e0d\u4e0a\u5065\u8eab\u623f\u81ea\u7df4\u53ef\u4ee5\u55ce\uff1f"}, "threadStatus": 0, "regionId": 886, "barStatus": 0, "barId": 719, "postBy": {"utc": 1518857584000, "level": 2, "location": "\u9ad8\u96c4\u5e02\u00b7\u53f0\u7063", "avatar": "http://filestoresg1.beetalkmobile.com:8081/file/-1389805785393672889", "name": "\u5e74\u53d4\u4e0a\ud83d\uddfb\u5c71\ud83d\udeb5\u9a0e\u4e0d\u5feb\ud83d\udeab"}, "id": 7730638}
