{"forum": {"content": "\u9727\u53f0\u9b6f\u51f1\u5973\u5b69\ud83d\udc95  \u4f86\u8a8d\u8b58\u4e00\u4e0b\u5427\uff01<br />   \u6211\u5f88\u597d\u76f8\u8655\u7684  \u5f88\u96a8\u548c\ud83d\ude0a <br />   \u4f86\u966a\u6211\u9019\u500b\u908a\u7de3\u4eba\u804a\u804a\u5929\u5427\u597d\u561b\ud83d\ude4f", "images": ["http://filestoresg1.beetalkmobile.com:8081/file/113c168d41bb3d69dc0bbbe7378c615a"], "urls": [], "title": "\u9019\u6a23\u7684\u6211\u53ef\u4ee5\u561b~\ud83d\udc7b"}, "threadStatus": 0, "regionId": 886, "barStatus": 0, "barId": 727, "postBy": {"utc": 1512970139000, "level": 3, "location": "\u65b0\u5317\u5e02\u00b7\u53f0\u7063", "avatar": "http://filestoresg1.beetalkmobile.com:8081/file/7671996338151954327", "name": "\ud83d\ude0a"}, "id": 7219543}
