{"forum": {"content": "\u6211\u60f3\uff0c\u4e00\u500b\u4eba\u7684\u4eba\u751f\u4e2d<br /><br />\u5f88\u96e3\u53bb\u53ea\u6709\u4e00\u6bb5\u611f\u60c5<br /><br />\u90fd\u6703\u9762\u5c0d\u632b\u6298\u96e3\u904e<br /><br />\u5176\u5be6\u5728\u9019\u904e\u7a0b\u4e2d\uff0c\u6bdb\u5c0f\u5b69\u5011\u7e3d\u662f\u7d66\u8207\u5fc3\u9748\u4e0a\u7684\u5b89\u6170<br /><br />\u4ed6\u5011\u7e3d\u662f\u4e0d\u96e2\u4e0d\u68c4<br /><br />\u7121\u8ad6\u662f\u611b\u60c5\u8def\u4e0a\uff0c\u53cb\u60c5\u8def\u4e0a\uff0c\u51fa\u793e\u6703\u4e4b\u5f8c\u7684\u78e8\u7df4<br /><br />\ud83d\ude19\ud83d\ude19\ud83d\ude19\ud83d\ude19<br /><br />\u9019\u90e8\u96fb\u5f71\u662f\u5728\u63cf\u8ff0\u4e00\u500b\u6bd2\u87f2\u60f3\u6539\u904e\u81ea\u65b0<br /><br />\u88e1\u9762\u63d0\u5230\uff0c\u6bcf\u500b\u4eba\u90fd\u6703\u6709\u7b2c\u4e8c\u6b21\u6a5f\u6703<br /><br />\u4f46\uff0c\u4e0d\u662f\u6bcf\u500b\u4eba\u90fd\u53ef\u4ee5\u5f88\u5e78\u904b\u7684\u6293\u4f4f\u9019\u500b\u6a5f\u6703<br /><br />\u4eba\u751f\u5c31\u9019\u9ebc\u4e00\u6b21<br /><br />\u6b7b\u4e86\u4ec0\u9ebc\u90fd\u6c92\u6709\u6a5f\u6703\u4e86<br /><br />\u6240\u4ee5\u5927\u5bb6\u597d\u597d\u73cd\u60dc\u773c\u524d\u7684\u4eba  \u4e8b  \u7269\u5537\uff01<br /><br />", "images": ["http://filestoresg1.beetalkmobile.com:8081/file/f47adb7c88d2797ede9cb5d2b07c42dc", "http://filestoresg1.beetalkmobile.com:8081/file/01771947e4d6799f0ed5d0495b248189", "http://filestoresg1.beetalkmobile.com:8081/file/fc78018096c5b0eeda0f1d17ec360bfe"], "urls": [], "title": "\u9047\u898b\u8857\u8c93BOB"}, "threadStatus": 0, "regionId": 886, "barStatus": 0, "barId": 13, "postBy": {"utc": 1512967887000, "level": 10, "location": "\u53f0\u5317\u5e02\u00b7\u53f0\u7063", "avatar": "http://filestoresg1.beetalkmobile.com:8081/file/3619208564831554477", "name": "Hades & Demon"}, "id": 7219263}
