{"forum": {"content": "\u53ef\u505a\u670b\u53cb \u90fd\u4f86<br />19y  \u563b\u563b", "images": ["http://filestoresg1.beetalkmobile.com:8081/file/9b54e9967d5c992db7c02e0fcb06a222", "http://filestoresg1.beetalkmobile.com:8081/file/0e044d476844c3efa900b568f99a1d3f", "http://filestoresg1.beetalkmobile.com:8081/file/5f2721a4ef1cf722a9783b9624ee336b"], "urls": [], "title": "\u8a8d\u8b58"}, "threadStatus": 0, "regionId": 886, "barStatus": 0, "barId": 32, "postBy": {"utc": 1516916003000, "level": 1, "location": "\u9ad8\u96c4\u5e02\u00b7\u53f0\u7063", "avatar": "http://filestoresg1.beetalkmobile.com:8081/file/102649319594046521", "name": "\u5c0f\u5c0f\u767d"}, "id": 7558572}
