{"forum": {"content": "\u5982\u984c", "images": ["http://filestoresg1.beetalkmobile.com:8081/file/2d5379d13cbbf4e940e5ee4a3c81de0b", "http://filestoresg1.beetalkmobile.com:8081/file/484cebf4f32732c3727e49272e9707d9", "http://filestoresg1.beetalkmobile.com:8081/file/514a9678647bb8f3463c2fe00e031bea", "http://filestoresg1.beetalkmobile.com:8081/file/910f19bcbb85ba08b8b975c59b958487"], "urls": [], "title": "\u81ea\u62cd\u4e00\u4e0b"}, "threadStatus": 1, "regionId": 886, "barStatus": 0, "barId": 4, "postBy": {"utc": 1518017238000, "level": 9, "location": "", "avatar": "http://filestoresg1.beetalkmobile.com:8081/file/-5388368936318659584", "name": "\u7121"}, "id": 7657577}
