{"forum": {"content": "\ud83d\ude42\u6211\u9019\u4eba\u5f88\u7c21\u55ae\u5728\u4e2d\u90e8\u5c31\u78ba\u8a8d\u597d\u53cb<br /><br />", "images": ["http://filestoresg1.beetalkmobile.com:8081/file/4795cfaec3e203a2c3f96bfe0044d764"], "urls": [], "title": "2018\u60f3\u9047\u5230\u80fd\u8b93\u6211\u522a\u871c\u8702\u7684\u59d0\u59d0"}, "threadStatus": 1, "regionId": 886, "barStatus": 0, "barId": 734, "postBy": {"utc": 1520716565000, "level": 4, "location": "\u53f0\u4e2d\u5e02\u00b7\u53f0\u7063", "avatar": "http://filestoresg1.beetalkmobile.com:8081/file/3343389461518298211", "name": "181"}, "id": 7907420}
