{"forum": {"content": "\u672c\u8eab\u4e0d\u60f3\u751f\u5c0f\u5b69\uff0c\u5982\u679c\u6709\u89c0\u5ff5\u76f8\u540c\u7684\uff0c\u6216\u662f\u96e2\u5a5a\u6709\u5c0f\u5b69\u7684\uff0c\u90fd\u53ef\u4ee5\u8a8d\u8b58\u4e00\u4e0b", "images": ["http://filestoresg1.beetalkmobile.com:8081/file/b6d87086a648f461fbef96b953899fe6"], "urls": [], "title": "\u6709\u6c92\u6709\u60f3\u7576\u9802\u5ba2\u65cf\uff0c\u6216\u96e2\u5a5a\u6709\u5c0f\u5b69\u7684\uff0c\u53ef\u4ee5\u8a8d\u8b58\u4e00\u4e0b"}, "threadStatus": 0, "regionId": 886, "barStatus": 0, "barId": 205, "postBy": {"utc": 1518683229000, "level": 1, "location": "\u53f0\u7063", "avatar": "http://filestoresg1.beetalkmobile.com:8081/file/-3459735375480832143", "name": "\u5c39"}, "id": 7715972}
