{"forum": {"content": "\u8aa0\u5fb5\u6211\u919c\u919c\uff0c\u77ee\u77ee", "images": ["http://filestoresg1.beetalkmobile.com:8081/file/ab3a221b434391e7e2487cb34e49cbd8"], "urls": [], "title": "\u5fb5\u6bcf\u5e74\u8de8\u5e74\u4f34"}, "threadStatus": 0, "regionId": 886, "barStatus": 0, "barId": 205, "postBy": {"utc": 1513706657000, "level": 2, "location": "\u53f0\u4e2d\u5e02\u00b7\u53f0\u7063", "avatar": "http://filestoresg1.beetalkmobile.com:8081/file/1355645074025309177", "name": "\u7032\u6cb3"}, "id": 7280226}
