{"forum": {"content": "\u66b4\u98a8\u96ea\u4e4b\u5f8c \u26c4<br /><br />\" Kindness is like snow. It beautifies everything it covers \"", "images": ["http://filestoresg1.beetalkmobile.com:8081/file/840f6c64ca6350f33f062754abfb333a", "http://filestoresg1.beetalkmobile.com:8081/file/7d575fc9efb040b74cff79c5f777b3cd", "http://filestoresg1.beetalkmobile.com:8081/file/6f333c0957218d44a12bd27cbe60dbaa", "http://filestoresg1.beetalkmobile.com:8081/file/2e4a890d26c96603d96f74b743aa1143", "http://filestoresg1.beetalkmobile.com:8081/file/d245c8f8d3795aab88c4930ac8e85881", "http://filestoresg1.beetalkmobile.com:8081/file/fd62300ce8753f8f29b80399418ad231"], "urls": [], "title": "\u8377\u862d \u9280\u767d\u8272\u7684\u96ea\u570b"}, "threadStatus": 0, "regionId": 886, "barStatus": 0, "barId": 85, "postBy": {"utc": 1512954097000, "level": 12, "location": "Noord-Holland\u00b7\u8377\u862d", "avatar": "http://filestoresg1.beetalkmobile.com:8081/file/2455209231958474413", "name": "Ester"}, "id": 7218101}
