{"forum": {"content": "\u6211\u7684\u6bcf\u4f4d\u597d\u53cb\uff0c\u5f88\u62b1\u6b49\u6211\u4e0d\u80fd\u6bcf\u5929\u4e0a\u7dda\uff0c\u56e0\u70ba\u6700\u8fd1\u5f88\u5fd9\u5b78\u6821\u6709\u5f88\u591a\u6d3b\u52d5\u800c\u4e14\u5feb\u8003\u8a66\u4e86", "images": ["http://filestoresg1.beetalkmobile.com:8081/file/4db5171955130cc94a0d27e9681e0957"], "urls": [], "title": "\u62b1\u6b49\uff0c\uff0c"}, "threadStatus": 0, "regionId": 886, "barStatus": 0, "barId": 769, "postBy": {"utc": 1511275803000, "level": 4, "location": "\u65b0\u5317\u5e02\u00b7\u53f0\u7063", "avatar": "http://filestoresg1.beetalkmobile.com:8081/file/4942145358263987631", "name": "\u6c34\u82b1\u6372\u6d6a"}, "id": 7082685}
