{"forum": {"content": "\u6709\u4eba\u6709\u628a\u63e1\u53ef\u4ee5\u7d66\u4ed6\u7b2c\u4e8c\u500b\u5bb6\u55ce", "images": ["http://filestoresg1.beetalkmobile.com:8081/file/faa7573ff9ca9f3d4deebaf1b613501a"], "urls": [], "title": "\u5bb6\u4eba\u4e0d\u7d66\u990a\uff0c\u5e36\u56de\u71df\u5340\u990a"}, "threadStatus": 1, "regionId": 886, "barStatus": 0, "barId": 751, "postBy": {"utc": 1510592392000, "level": 4, "location": "\u53f0\u5317\u5e02\u00b7\u53f0\u7063", "avatar": "http://filestoresg1.beetalkmobile.com:8081/file/-1967777267629325620", "name": "Su"}, "id": 7026623}
