{"forum": {"content": "\u665a\u4e0a\u53f0\u4e2dMUSE \u6709\u4eba\u8981\u4e00\u8d77\u55ce", "images": ["http://filestoresg1.beetalkmobile.com:8081/file/6e7141d1d570cb24a5f647e1ec717ad3"], "urls": [], "title": "\u665a\u4e0a\u6709\u4eba\u8981\u4e00\u8d77\u591c\u5e97\u55ce"}, "threadStatus": 0, "regionId": 886, "barStatus": 0, "barId": 792, "postBy": {"utc": 1518941293000, "level": 3, "location": "\u82d7\u6817\u7e23\u00b7\u53f0\u7063", "avatar": "http://filestoresg1.beetalkmobile.com:8081/file/-847699266778103794", "name": "\u4f5b\u7cfb\u7537\u5b69"}, "id": 7737970}
