{"forum": {"content": "\u53ef\u4ee5\u6210\u719f\u7a69\u91cd\uff0c\u4e5f\u53ef\u4ee5\u6492\u6492\u5b0c<br />\u53ef\u4ee5\u4e92\u5bf5\u4e92\u64a9<br /><br />17\uff0c\u9999\u6e2f", "images": ["http://filestoresg1.beetalkmobile.com:8081/file/0be9697184065a458356f2a5513ebafb"], "urls": [], "title": "\u627e\u500b\u5973\u751f\u804a\u51fa\u611f\u60c5"}, "threadStatus": 0, "regionId": 886, "barStatus": 0, "barId": 20, "postBy": {"utc": 1516714879000, "level": 1, "location": "", "avatar": "http://filestoresg1.beetalkmobile.com:8081/file/2061458969015965288", "name": "\u58a8\u7464"}, "id": 7539598}
