{"forum": {"content": "\u58d3\u529b\u5927\ud83d\ude2b\ud83d\ude2b\ud83d\ude2b", "images": ["http://filestoresg1.beetalkmobile.com:8081/file/084fb96f5d1ea2b8906ecae5a51021b0"], "urls": [], "title": "\u8a0e\u53ad\u8003\u8a66\u6b38"}, "threadStatus": 0, "regionId": 886, "barStatus": 0, "barId": 4, "postBy": {"utc": 1516179859000, "level": 2, "location": "\u65b0\u5317\u5e02\u00b7\u53f0\u7063", "avatar": "http://filestoresg1.beetalkmobile.com:8081/file/-1631901730904621907", "name": "Claire"}, "id": 7489573}
