{"forum": {"content": "\u4e8c\u5e74\u5167\u7684\u81ea\u62cd\u7167\uff0c\u5927\u5bb6\u89ba\u5f97\u597d\u770b\u55ce?", "images": ["http://filestoresg1.beetalkmobile.com:8081/file/bdf98fc4a2ccc9edaa668c2dd996786a", "http://filestoresg1.beetalkmobile.com:8081/file/71b4f033b7bc0cee1fcd589393ad3b80", "http://filestoresg1.beetalkmobile.com:8081/file/2819fe535d5cbb8be46b66c042b07d1e", "http://filestoresg1.beetalkmobile.com:8081/file/ff487d876ec0a8c3087856fe13134258", "http://filestoresg1.beetalkmobile.com:8081/file/316e54854347f11ef1a5742e13e7e384"], "urls": [], "title": "\u81ea\u62cd\u7167"}, "threadStatus": 0, "regionId": 886, "barStatus": 0, "barId": 4, "postBy": {"utc": 1517061545000, "level": 2, "location": "\u65b0\u5317\u5e02\u00b7\u53f0\u7063", "avatar": "http://filestoresg1.beetalkmobile.com:8081/file/6600684968996731055", "name": "\u5be7\u5152"}, "id": 7571561}
