{"forum": {"content": "\u54c8\u56c9\u6211\u627e\u59d0\u59d0\u75bc\u611b\u554a \ud83d\ude08\ud83d\ude08", "images": ["http://filestoresg1.beetalkmobile.com:8081/file/8050cf9bfa468018ebf1e5652660154c"], "urls": [], "title": "\u9ad8\u96c421"}, "threadStatus": 0, "regionId": 886, "barStatus": 0, "barId": 734, "postBy": {"utc": 1515144801000, "level": 1, "location": "\u9ad8\u96c4\u5e02\u00b7\u53f0\u7063", "avatar": "http://filestoresg1.beetalkmobile.com:8081/file/-3272412664285292799", "name": "Chuan"}, "id": 7396751}
