{"forum": {"content": "\u6cb9\u5ee0\u570b\u5c0f\u5916\u62cd", "images": ["http://filestoresg1.beetalkmobile.com:8081/file/2d08284ba81e36389999f4b2feb5f177", "http://filestoresg1.beetalkmobile.com:8081/file/c28f748527e840626fa38a4480d3d13f", "http://filestoresg1.beetalkmobile.com:8081/file/8529bd05aa847872c36d3e78f780795b", "http://filestoresg1.beetalkmobile.com:8081/file/e3c1a943eb3e231189f4f6df8a4d536e", "http://filestoresg1.beetalkmobile.com:8081/file/f2971c33e14bff1cf1861c64348d5cd8", "http://filestoresg1.beetalkmobile.com:8081/file/f7f8b76ab3accff7f719f4fb15edcbd7"], "urls": [], "title": "\u5916\u62cd\u4f5c\u54c1\u5206\u4eab"}, "threadStatus": 0, "regionId": 886, "barStatus": 0, "barId": 77, "postBy": {"utc": 1511135987000, "level": 12, "location": "\u9ad8\u96c4\u5e02\u00b7\u53f0\u7063", "avatar": "http://filestoresg1.beetalkmobile.com:8081/file/-6770496833535252211", "name": "\u79c9\u6f8d"}, "id": 7070953}
