{"forum": {"content": "\u6b61\u6a02\u6253 \u4e0d\u66b4\u6012\u5c31\u597d rk ng\u90fdok\u7f3a\u597d\u53cb\u5440\ud83d\ude02<br /><br />\u6b61\u8fce\u52a0\u6211\u597d\u53cb\u6216\u7559Id", "images": ["http://filestoresg1.beetalkmobile.com:8081/file/73a6b7a88277fa8b8fbca17bf248a994"], "urls": [], "title": "\u908a\u7de3\u4eba\u627e\u6230\u53cb"}, "threadStatus": 0, "regionId": 886, "barStatus": 0, "barId": 60, "postBy": {"utc": 1521523658000, "level": 2, "location": "", "avatar": "http://filestoresg1.beetalkmobile.com:8081/file/-2809332469887459584", "name": "\u6607\u2600\ufe0f"}, "id": 7987836}
