{"forum": {"content": "  ", "images": [], "urls": [{"url": "https://www.facebook.com/groups/133442303660645/permalink/624560071215530/", "thumbUrl": "https://scontent-sit4-1.xx.fbcdn.net/v/t15.0-10/s403x403/27853818_171686756889333_8879602772878557184_n.jpg?oh=b55d4239e8070eaee2568f727d1bc855&oe=5B25DA08", "description": "\u9ad8\u624b\u5728\u6c11\u95f4", "title": "\u9ad8\u5927\u4e2d"}], "title": "\u9ad8\u624b"}, "threadStatus": 0, "regionId": 886, "barStatus": 0, "barId": 10, "postBy": {"utc": 1518970605000, "level": 0, "location": "\u81fa\u7063\u7701\u00b7\u53f0\u7063", "avatar": "http://filestoresg1.beetalkmobile.com:8081/file/-8832780408035807949", "name": "\u78a9\u54e5"}, "id": 7741628}
