{"forum": {"content": "\u5404\u4f4d\uff0c\u5982\u679c\u4f86\u500b\u5927\u53d4\u805a\u6703\u22ef<br />\u4f60\u5011\u89ba\u5f97\u8207\u6703\u4eba\u6578<br />\u662f\u5927\u53d4\u591a\uff1f<br />\u9084\u662f\u5927\u53d4\u63a7\u591a\uff1f", "images": ["http://filestoresg1.beetalkmobile.com:8081/file/b963543f6854cac3aa33df1a92c70bef"], "urls": [], "title": "\u5927\u53d4\u805a\u67032018"}, "threadStatus": 0, "regionId": 886, "barStatus": 0, "barId": 838, "postBy": {"utc": 1513614469000, "level": 7, "location": "", "avatar": "http://filestoresg1.beetalkmobile.com:8081/file/-9134785460620507392", "name": "SBJR"}, "id": 7272959}
