{"forum": {"content": "Hi. \u8b1d\u8b1d\u59b3\u9ede\u9032\u4f86\uff01<br /><br />\u55ae\u8eab<br /><br />\u6211\u89ba\u5f97\u9069\u5a5a\u5e74\u9f61\uff0c\u6211\u5011\u804a\u804a\u59b3\u8aaa\u5462\uff1f", "images": ["http://filestoresg1.beetalkmobile.com:8081/file/0f034c28fb824be1da8ac61c389bd9dd"], "urls": [], "title": "\u9069\u5a5a\u5e74\u9f61\uff01\u6843\u7af9\u82d7\u4f73\uff0c\u6211\u89ba\u5f97\u53ef\u4ee5\u804a\u804a"}, "threadStatus": 0, "regionId": 886, "barStatus": 0, "barId": 740, "postBy": {"utc": 1517673600000, "level": 1, "location": "\u65b0\u7af9\u5e02\u00b7\u53f0\u7063", "avatar": "http://filestoresg1.beetalkmobile.com:8081/file/-6964862986644588032", "name": "old child"}, "id": 7627339}
