{"forum": {"content": "\u8def\u904e~~\u89ba\u5f97\u53ef\u4ee5", "images": ["http://filestoresg1.beetalkmobile.com:8081/file/b5f1d414d6459d6998bb8418881508da"], "urls": [], "title": "\u65b0\u7af9  \u9d28\u8089\u8a31"}, "threadStatus": 0, "regionId": 886, "barStatus": 0, "barId": 98, "postBy": {"utc": 1514357676000, "level": 8, "location": "\u6843\u5712\u5e02\u00b7\u53f0\u7063", "avatar": "http://filestoresg1.beetalkmobile.com:8081/file/3289130761835397347", "name": "\u8ca2\u8ca2\u9999\ud83c\udf54"}, "id": 7331469}
