{"forum": {"content": "\u56e0\u70ba<br />\u22ef<br /><br /><br /><br /><br /><br /><br /><br /><br /><br /><br />\u59b3\u9084\u6c92\u6709\u9047\u5230\u5e6b\u59b3\u5be6\u73fe\u9858\u671b\u7684\u6211\ud83e\udd14\ud83d\ude02<br /><br />\u6b61\u8fce\u52a0\u5165\u64a9\u59b9\u884c\u5217\ud83d\udc4f", "images": ["http://filestoresg1.beetalkmobile.com:8081/file/526dde86589481bbcf4bed613ddfe840"], "urls": [], "title": "\u59b3\u77e5\u9053\u70ba\u4ec0\u9ebc\u5c0d\u8457\u6d41\u661f\u8a31\u9858\u8001\u662f\u4e0d\u6703\u5be6\u73fe\u5462\uff1f"}, "threadStatus": 0, "regionId": 886, "barStatus": 0, "barId": 20, "postBy": {"utc": 1510997880000, "level": 2, "location": "", "avatar": "http://filestoresg1.beetalkmobile.com:8081/file/-3337179417086711808", "name": "\u2728\u71e6\u5b87\ud83d\udcab\ud83c\udf1a\ud83c\udf1a"}, "id": 7059073}
