{"forum": {"content": "Good\u2764\ufe0f", "images": [], "urls": [{"url": "https://youtu.be/sdm29nRdABM", "thumbUrl": "https://i.ytimg.com/vi/sdm29nRdABM/hqdefault.jpg", "description": "Martin Garrix & David Guetta - So Far Away (feat. Jamie Scott, Romy Dya) \u2705 Could you support Royal M", "title": "Martin Garrix & David Guetta - So Far Away (feat. Jamie Scott, Romy Dya)"}], "title": "\ud83d\ude4c\ud83c\udffb\ud83d\ude4c\ud83c\udffb\ud83d\ude4c\ud83c\udffb"}, "threadStatus": 0, "regionId": 886, "barStatus": 0, "barId": 54, "postBy": {"utc": 1512869137000, "level": 1, "location": "\u9ad8\u96c4\u5e02\u00b7\u53f0\u7063", "avatar": "http://filestoresg1.beetalkmobile.com:8081/file/8337998016062784786", "name": "\u7a4e\u5a55"}, "id": 7210699}
