{"forum": {"content": "\u8ffd\u6211\u5509\u5c45\u597d\u55ce\ud83d\ude33\ud83d\ude33\ud83d\ude33<br />0929.__.ian", "images": ["http://filestoresg1.beetalkmobile.com:8081/file/828d6e839e8f6e1472df875dbcef4361"], "urls": [], "title": "\u4f86\u8a8d\u8b58\u2764"}, "threadStatus": 0, "regionId": 886, "barStatus": 0, "barId": 512, "postBy": {"utc": 1518973722000, "level": 7, "location": "\u53f0\u5317\u5e02\u00b7\u53f0\u7063", "avatar": "http://filestoresg1.beetalkmobile.com:8081/file/-4974707356812701844", "name": "\u522a"}, "id": 7742015}
