{"forum": {"content": "10\u9ede\u7684\u8eca\u524d\u5f80\u6a5f\u5834\uff0c\u773c\u770b\u5df2\u7d938\u9ede\u4e86\uff0c\u53ea\u5269\u4e0d\u5230\u5169\u5c0f\u6642\uff0c\u70ba\u4e86\u652f\u6301\u7684\u5718\u53cb\u5011\uff0c\u885d\uff01\u885d\uff01\u885d\uff01\u7279\u5730\u642dJR\u8dd1\u53bb\u4e00\u8d9f\u3002\u6c92\u60f3\u5230\u4e00\u65e9\u5c31\u9019\u9ebc\u591a\u4eba\u6392\u968a\ud83d\ude0b", "images": ["http://filestoresg1.beetalkmobile.com:8081/file/bc22f35960c4e4e5611dca8184c77a4d", "http://filestoresg1.beetalkmobile.com:8081/file/5e0a3ca49826a5c64589a68af6b1fe55"], "urls": [], "title": "\u6771\u4eac\u8eca\u7ad9-\u6025\u4ef6\u7684\u4f34\u624b\u79ae\uff01\uff01"}, "threadStatus": 1, "regionId": 886, "barStatus": 0, "barId": 87, "postBy": {"utc": 1515983473000, "level": 1, "location": "", "avatar": "http://filestoresg1.beetalkmobile.com:8081/file/-818014655507490282", "name": "\u6b50\u5df4?\u5927\u53d4?"}, "id": 7472071}
