{"forum": {"content": "\u9084\u662f\u6211\u7e7c\u7e8c\u7761\u597d\u4e86\ud83d\ude02", "images": ["http://filestoresg1.beetalkmobile.com:8081/file/8dbc60b2e68113b9a38215f6c1c6f1c7"], "urls": [], "title": "\u627e\u4eba\u4e00\u8d77\u770b\u863f\u62c9\u22ef\u22ef"}, "threadStatus": 0, "regionId": 886, "barStatus": 0, "barId": 205, "postBy": {"utc": 1520497718000, "level": 2, "location": "\u53f0\u4e2d\u5e02\u00b7\u53f0\u7063", "avatar": "http://filestoresg1.beetalkmobile.com:8081/file/5326182762995416576", "name": "\u7da0\u8336"}, "id": 7886248}
