{"forum": {"content": "\u7c21\u55ae\u7684\u62cd\uff0c\u591a\u5305\u6db5", "images": ["http://filestoresg1.beetalkmobile.com:8081/file/f0c00bb6ab4ceb6c50140e1eb8f81747", "http://filestoresg1.beetalkmobile.com:8081/file/9a30972644fd7c8d7c932d294d3186c0", "http://filestoresg1.beetalkmobile.com:8081/file/e270aa3d94136547ca9e3dead4214e79", "http://filestoresg1.beetalkmobile.com:8081/file/3c4af4613a2d160ba056d43413651ba2", "http://filestoresg1.beetalkmobile.com:8081/file/9bc828b45e580321fb38fcf33f083f76", "http://filestoresg1.beetalkmobile.com:8081/file/1fc35dc4c8987e4e79731a864f7add64"], "urls": [], "title": "\u5e7e\u5ea6\u5915\u967d\u7d05\uff0c\u770b\u770b\u5c31\u597d"}, "threadStatus": 0, "regionId": 886, "barStatus": 0, "barId": 77, "postBy": {"utc": 1520785234000, "level": 18, "location": "\u65b0\u5317\u5e02\u00b7\u53f0\u7063", "avatar": "http://filestoresg1.beetalkmobile.com:8081/file/-8616770364482356193", "name": "\u6751\u4e0a\u5c0f\u53d4"}, "id": 7914525}
